{
  "Workers": [
    {
      "id": 1,
      "firstName": "John",
      "secondName": "Doe",
      "email": "john.doe@example.com",
      "officialEmail": "john.doe@company.com",
      "mobile": "1234567890",
      "onboardingStatus": "Completed",
      "department": "Engineering",
      "active": "yes",
      "action": "view"
    },
    {
      "id": 2,
      "firstName": "Jane",
      "secondName": "Smith",
      "email": "jane.smith@example.com",
      "officialEmail": "jane.smith@company.com",
      "mobile": "1234567891",
      "onboardingStatus": "In Progress",
      "department": "Marketing",
      "active": "yes",
      "action": "view"
    },
    {
      "id": 3,
      "firstName": "Alice",
      "secondName": "Brown",
      "email": "alice.brown@example.com",
      "officialEmail": "alice.brown@company.com",
      "mobile": "1234567892",
      "onboardingStatus": "Pending",
      "department": "HR",
      "active": "no",
      "action": "view"
    },
    {
      "id": 4,
      "firstName": "Bob",
      "secondName": "Williams",
      "email": "bob.williams@example.com",
      "officialEmail": "bob.williams@company.com",
      "mobile": "1234567893",
      "onboardingStatus": "Completed",
      "department": "Finance",
      "active": "yes",
      "action": "view"
    },
    {
      "id": 5,
      "firstName": "Charlie",
      "secondName": "Davis",
      "email": "charlie.davis@example.com",
      "officialEmail": "charlie.davis@company.com",
      "mobile": "1234567894",
      "onboardingStatus": "In Progress",
      "department": "Sales",
      "active": "yes",
      "action": "view"
    },
    {
      "id": 6,
      "firstName": "Eve",
      "secondName": "Taylor",
      "email": "eve.taylor@example.com",
      "officialEmail": "eve.taylor@company.com",
      "mobile": "1234567895",
      "onboardingStatus": "Pending",
      "department": "Support",
      "active": "no",
      "action": "view"
    },
    {
      "id": 7,
      "firstName": "Frank",
      "secondName": "Clark",
      "email": "frank.clark@example.com",
      "officialEmail": "frank.clark@company.com",
      "mobile": "1234567896",
      "onboardingStatus": "Completed",
      "department": "Engineering",
      "active": "yes",
      "action": "view"
    },
    {
      "id": 8,
      "firstName": "Grace",
      "secondName": "Lee",
      "email": "grace.lee@example.com",
      "officialEmail": "grace.lee@company.com",
      "mobile": "1234567897",
      "onboardingStatus": "In Progress",
      "department": "Design",
      "active": "yes",
      "action": "view"
    },
    {
      "id": 9,
      "firstName": "Hank",
      "secondName": "Adams",
      "email": "hank.adams@example.com",
      "officialEmail": "hank.adams@company.com",
      "mobile": "1234567898",
      "onboardingStatus": "Pending",
      "department": "IT",
      "active": "no",
      "action": "view"
    },
    {
      "id": 10,
      "firstName": "Ivy",
      "secondName": "Thomas",
      "email": "ivy.thomas@example.com",
      "officialEmail": "ivy.thomas@company.com",
      "mobile": "1234567899",
      "onboardingStatus": "Completed",
      "department": "Operations",
      "active": "yes",
      "action": "view"
    }
  ]
}